transcribe_zh_en_srt/__init__.py
transcribe_zh_en_srt/main.py
transcribe_zh_en_srt-0.4.dist-info/METADATA
transcribe_zh_en_srt-0.4.dist-info/WHEEL
transcribe_zh_en_srt-0.4.dist-info/entry_points.txt
transcribe_zh_en_srt-0.4.dist-info/top_level.txt
transcribe_zh_en_srt-0.4.dist-info/RECORD
