Metadata-Version: 2.1
Name: transcribe-zh-en-srt
Version: 0.4
Summary: A package to process audio and generate translation from input language to target language. this package return srt format files containing english accurated translation from Chinese language to English language.
Home-page: https://github.com/Abdulhamid97Mousa/transcribe_zh_en_p2
Author: Zahra Daoui
Author-email: zahradaoui4@gmail.com
License: UNKNOWN
Platform: UNKNOWN
Classifier: Programming Language :: Python :: 3.8
Classifier: License :: OSI Approved :: MIT License
Classifier: Operating System :: OS Independent
Requires-Dist: torch==2.4.1
Requires-Dist: triton==3.0.0
Requires-Dist: python-dotenv
Requires-Dist: demucs==4.0.1
Requires-Dist: omegaconf==2.3.0
Requires-Dist: openunmix==1.2.1
Requires-Dist: requests==2.32.3
Requires-Dist: retrying==1.3.4
Requires-Dist: six==1.16.0
Requires-Dist: submitit==1.5.2
Requires-Dist: sympy==1.13.3
Requires-Dist: wheel==0.45.1
Requires-Dist: numpy==1.23.5
